pytoolbelt/__init__.py
pytoolbelt/__main__.py
pytoolbelt/cli/__init__.py
pytoolbelt/cli/controllers/common.py
pytoolbelt/cli/controllers/format_controller.py
pytoolbelt/cli/controllers/init_controller.py
pytoolbelt/cli/controllers/installed_controller.py
pytoolbelt/cli/controllers/ptvenv_controller.py
pytoolbelt/cli/controllers/release_controller.py
pytoolbelt/cli/controllers/releases_controller.py
pytoolbelt/cli/controllers/test_controller.py
pytoolbelt/cli/controllers/tool_controller.py
pytoolbelt/cli/controllers/toolbelt_controller.py
pytoolbelt/cli/entrypoints/ptvenv_entrypoints.py
pytoolbelt/cli/entrypoints/test_entrypoints.py
pytoolbelt/cli/entrypoints/tool_entrypoints.py
pytoolbelt/cli/entrypoints/toolbelt_entrypoints.py
pytoolbelt/cli/entrypoints/bases/__init__.py
pytoolbelt/cli/entrypoints/bases/base_context.py
pytoolbelt/cli/entrypoints/bases/base_parameters.py
pytoolbelt/cli/parsers/format.py
pytoolbelt/cli/parsers/init.py
pytoolbelt/cli/parsers/installed.py
pytoolbelt/cli/parsers/ptvenv.py
pytoolbelt/cli/parsers/release.py
pytoolbelt/cli/parsers/releases.py
pytoolbelt/cli/parsers/test.py
pytoolbelt/cli/parsers/tool.py
pytoolbelt/cli/parsers/toolbelt.py
pytoolbelt/cli/views/base_view.py
pytoolbelt/cli/views/installed_view.py
pytoolbelt/cli/views/ptvenv_views.py
pytoolbelt/cli/views/releases_view.py
pytoolbelt/cli/views/tool_views.py
pytoolbelt/cli/views/toolbelt_views.py
pytoolbelt/core/prompts.py
pytoolbelt/core/bases/base_paths.py
pytoolbelt/core/bases/base_templater.py
pytoolbelt/core/data_classes/component_metadata.py
pytoolbelt/core/data_classes/pytoolbelt_config.py
pytoolbelt/core/data_classes/toolbelt_config.py
pytoolbelt/core/error_handling/error_handler.py
pytoolbelt/core/error_handling/exceptions.py
pytoolbelt/core/project/ptvenv_components.py
pytoolbelt/core/project/tool_components.py
pytoolbelt/core/project/toolbelt_components.py
pytoolbelt/core/tools/__init__.py
pytoolbelt/core/tools/formatting.py
pytoolbelt/core/tools/git_client.py
pytoolbelt_cli-0.6.5.dist-info/LICENSE
pytoolbelt_cli-0.6.5.dist-info/METADATA
pytoolbelt_cli-0.6.5.dist-info/WHEEL
pytoolbelt_cli-0.6.5.dist-info/entry_points.txt
pytoolbelt_cli-0.6.5.dist-info/top_level.txt
pytoolbelt_cli-0.6.5.dist-info/RECORD
