Metadata-Version: 2.1
Name: pytoolbelt-cli
Version: 0.6.5
Summary: A CLI tool to help teams share internal tooling written in python.
Project-URL: homepage, https://github.com/pytoolbelt/pytoolbelt-cli
Project-URL: documentation, https://pytoolbelt.github.io/pytoolbelt-cli/
Project-URL: changelog, https://github.com/pytoolbelt/pytoolbelt-cli/blob/main/CHANGELOG.md
Requires-Python: >=3.9
License-File: LICENSE
Requires-Dist: requests >=2.26.0
Requires-Dist: pydantic >=1.8.2
Requires-Dist: gitdb ==4.0.11
Requires-Dist: GitPython ==3.1.43
Requires-Dist: Jinja2 ==3.1.4
Requires-Dist: pydantic ==2.7.4
Requires-Dist: pydantic-core ==2.18.4
Requires-Dist: python-dotenv ==1.0.1
Requires-Dist: PyYAML ==6.0.1
Requires-Dist: semver ==3.0.2
Requires-Dist: giturlparse ==0.12.0
Requires-Dist: rich ==13.7.1
Requires-Dist: ruff ==0.5.5
Requires-Dist: docker ==7.1.0
Provides-Extra: dev
Requires-Dist: setuptools ==70.3.0 ; extra == 'dev'
Requires-Dist: build ==1.2.1 ; extra == 'dev'
Requires-Dist: python-semantic-release ==9.8.5 ; extra == 'dev'
Requires-Dist: pytest ==8.2.2 ; extra == 'dev'
Provides-Extra: docs
Requires-Dist: mkdocs ==1.6.0 ; extra == 'docs'
Requires-Dist: mkdocstrings-python ==1.10.5 ; extra == 'docs'
Requires-Dist: mkdocs-material ==9.5.29 ; extra == 'docs'
Requires-Dist: markdown-include ==0.8.1 ; extra == 'docs'
Provides-Extra: fmt
Requires-Dist: ruff ==0.5.5 ; extra == 'fmt'
